binodtharu/__init__.py
binodtharu/binodfile.py
binodtharu-2.8.dist-info/LICENSE
binodtharu-2.8.dist-info/METADATA
binodtharu-2.8.dist-info/WHEEL
binodtharu-2.8.dist-info/top_level.txt
binodtharu-2.8.dist-info/RECORD
