Metadata-Version: 2.1
Name: binodtharu
Version: 2.8
Summary: Binod
Home-page: https://github.com/forkbabu/BinodTharu
Author: Sayantan Das
Author-email: sayantandas30011998@gmail.com
License: UNKNOWN
Keywords: binod
Platform: UNKNOWN
Classifier: Programming Language :: Python :: 3
Classifier: License :: OSI Approved :: MIT License
Classifier: Operating System :: OS Independent
Requires-Python: >=3.6
Requires-Dist: wget
Requires-Dist: tqdm
